upinfopy/__init__.py
upinfopy/api78.py
upinfopy/upinfo.py
upinfopy-0.1.31.dist-info/entry_points.txt
upinfopy-0.1.31.dist-info/LICENSE
upinfopy-0.1.31.dist-info/METADATA
upinfopy-0.1.31.dist-info/WHEEL
upinfopy-0.1.31.dist-info/RECORD
