Metadata-Version: 2.1
Name: upinfopy
Version: 0.1.31
Summary: Python implementation of UpInfo78
Home-page: https://github.com/www778878net/UpinfoPy
License: Apache-2.0
Author: frieda
Author-email: www778878net@189.cn
Requires-Python: >=3.9
Classifier: License :: OSI Approved :: Apache Software License
Classifier: Programming Language :: Python :: 3
Classifier: Programming Language :: Python :: 3.9
Classifier: Programming Language :: Python :: 3.10
Classifier: Programming Language :: Python :: 3.11
Classifier: Programming Language :: Python :: 3.12
Classifier: Programming Language :: Python :: 3.13
Requires-Dist: invoke (>=1.7.0,<2.0.0)
Requires-Dist: requests (>=2.32.3,<3.0.0)
Project-URL: Documentation, http://www.778878.net/docs/#/upinfopy/
